fd_replay/__init__.py
fd_replay/classes/__init__.py
fd_replay/classes/config.py
fd_replay/classes/exceptions.py
fd_replay/classes/plugins.py
fd_replay/classes/target.py
fd_replay/modules/__init__.py
fd_replay/modules/replay.py
fd_replay/plugins/__init__.py
fd_replay/plugins/http.py
fd_replay-0.0.14.data/scripts/fd-replay
fd_replay-0.0.14.dist-info/DESCRIPTION.rst
fd_replay-0.0.14.dist-info/METADATA
fd_replay-0.0.14.dist-info/RECORD
fd_replay-0.0.14.dist-info/WHEEL
fd_replay-0.0.14.dist-info/metadata.json
fd_replay-0.0.14.dist-info/top_level.txt
