Metadata-Version: 2.0
Name: fd-replay
Version: 0.0.14
Summary: fd-replay
Home-page: https://github.com/decryptus/fd-replay
Author: Adrien Delle Cave
Author-email: pypi@doowan.net
License: License GPL-2
Platform: UNKNOWN
Requires-Dist: dwho (>=0.2.89)
Requires-Dist: httpdis (>=0.5.13)
Requires-Dist: pycurl
Requires-Dist: pyyaml (>=3.10)
Requires-Dist: sonicprobe (>=0.2.59)
Requires-Dist: requests (>=2.0)
